metadata_scanner.cpython-312-x86_64-linux-gnu.so
purple_bindings/__init__.py
purple_bindings/benchmark_purple_import.py
purple_bindings/python_example.py
purple_bindings/python_scan.py
purple_bindings/test_purple_import.py
purple_bindings-0.8.0.dist-info/METADATA
purple_bindings-0.8.0.dist-info/WHEEL
purple_bindings-0.8.0.dist-info/top_level.txt
purple_bindings-0.8.0.dist-info/RECORD
purple_bindings-0.8.0.dist-info/licenses/LICENSE
