Metadata-Version: 2.4
Name: purple_bindings
Version: 0.8.0
Summary: Fast C++ metadata scanner for disk cache
Author: Serapheim Dimitropoulos
Author-email: Serapheim Dimitropoulos <serapheim.dimitropoulos@weka.io>
License-Expression: MIT
Classifier: Development Status :: 3 - Alpha
Classifier: Intended Audience :: Developers
Classifier: Programming Language :: Python :: 3
Classifier: Programming Language :: Python :: 3.7
Classifier: Programming Language :: Python :: 3.8
Classifier: Programming Language :: Python :: 3.9
Classifier: Programming Language :: Python :: 3.10
Classifier: Programming Language :: Python :: 3.11
Classifier: Programming Language :: Python :: 3.12
Classifier: Programming Language :: C++
Requires-Python: >=3.7
License-File: LICENSE
Provides-Extra: dev
Requires-Dist: pytest; extra == "dev"
Requires-Dist: torch; extra == "dev"
Dynamic: author
Dynamic: license-file
Dynamic: requires-python
